.DS_Store
calcalc/CalCalc.py
calcalc/__init__.py
hw3_CalCalc_fm-0.0.3.dist-info/LICENSE.txt
hw3_CalCalc_fm-0.0.3.dist-info/METADATA
hw3_CalCalc_fm-0.0.3.dist-info/WHEEL
hw3_CalCalc_fm-0.0.3.dist-info/top_level.txt
hw3_CalCalc_fm-0.0.3.dist-info/RECORD
