Metadata-Version: 2.1
Name: hw3-CalCalc-fm
Version: 0.0.3
Summary: Calcalc module for hw3
Author: Fanhao Meng
Author-email: fhmeng@berkeley.edu
License: UNKNOWN
Project-URL: Source, https://github.com/fanhao-meng/python-ay250-homework
Keywords: calculate,ay250,wolfram,homework
Platform: UNKNOWN
Requires-Python: >=3.6, <4
License-File: LICENSE.txt
